MANIFEST.in
requirements.txt
setup.cfg
setup.py
test_requirements.txt
third_party_requirements.txt
version.txt
cloudshell/__init__.py
cloudshell/networking/__init__.py
cloudshell/networking/cisco/__init__.py
cloudshell/networking/cisco/cisco_configuration_operations.py
cloudshell/networking/cisco/cisco_connectivity_operations.py
cloudshell/networking/cisco/cisco_send_command_operations.py
cloudshell/networking/cisco/resource_drivers_map.py
cloudshell/networking/cisco/autoload/__init__.py
cloudshell/networking/cisco/autoload/cisco_generic_snmp_autoload.py
cloudshell/networking/cisco/command_templates/__init__.py
cloudshell/networking/cisco/command_templates/cisco_interface.py
cloudshell/networking/cisco/command_templates/ethernet.py
cloudshell/networking/cisco/command_templates/interfaces_configurator.py
cloudshell/networking/cisco/command_templates/mgmt.py
cloudshell/networking/cisco/command_templates/port_channel.py
cloudshell/networking/cisco/command_templates/vlan.py
cloudshell/networking/cisco/firmware_data/__init__.py
cloudshell/networking/cisco/firmware_data/cisco_firmware_data.py
cloudshell/networking/cisco/firmware_data/firmware_data.py
cloudshell/networking/cisco/mibs/CISCO-CDP-MIB.py
cloudshell/networking/cisco/mibs/CISCO-ENTITY-VENDORTYPE-OID-MIB.py
cloudshell/networking/cisco/mibs/CISCO-PRODUCTS-MIB.py
cloudshell/networking/cisco/mibs/CISCO-SMI.py
cloudshell/networking/cisco/mibs/CISCO-STACK-MIB.py
cloudshell/networking/cisco/mibs/CISCO-TC.py
cloudshell/networking/cisco/mibs/CISCO-VTP-MIB.py
cloudshell/networking/cisco/mibs/__init__.py
cloudshell/tests/__init__.py
cloudshell/tests/cloudshell_networking_cisco_tests.py
cloudshell/tests/networking/__init__.py
cloudshell/tests/networking/cisco/__init__.py
cloudshell/tests/networking/cisco/config_for_tests.py
cloudshell/tests/networking/cisco/connectivity_methods/__init__.py
cloudshell/tests/networking/cisco/connectivity_methods/test_apply_connectivity_changes.py
cloudshell_networking_cisco_beta.egg-info/PKG-INFO
cloudshell_networking_cisco_beta.egg-info/SOURCES.txt
cloudshell_networking_cisco_beta.egg-info/dependency_links.txt
cloudshell_networking_cisco_beta.egg-info/requires.txt
cloudshell_networking_cisco_beta.egg-info/top_level.txt