Metadata-Version: 1.0
Name: cloudshell-networking-cisco-beta
Version: 2.1.196
Summary: QualiSystems networking cisco specific package
Home-page: http://www.qualisystems.com/
Author: QualiSystems
Author-email: info@qualisystems.com
License: UNKNOWN
Platform: UNKNOWN
